yokatlas_py/__init__.py
yokatlas_py/base_fetcher.py
yokatlas_py/columnData.json
yokatlas_py/config.py
yokatlas_py/form_data.py
yokatlas_py/http_client.py
yokatlas_py/lisansatlasi.py
yokatlas_py/lisanstercihsihirbazi.py
yokatlas_py/models.py
yokatlas_py/onlisans_form_data.py
yokatlas_py/onlisansatlasi.py
yokatlas_py/onlisanstercihsihirbazi.py
yokatlas_py/search_utils.py
yokatlas_py/search_wrappers.py
yokatlas_py/utils.py
yokatlas_py/fetchers/__init__.py
yokatlas_py/fetchers/akademisyen_sayilari.py
yokatlas_py/fetchers/cinsiyet_dagilimi.py
yokatlas_py/fetchers/degisim_programi_bilgileri.py
yokatlas_py/fetchers/genel_bilgiler.py
yokatlas_py/fetchers/kayitli_ogrenci_cinsiyet_dagilimi.py
yokatlas_py/fetchers/kontenjan_yerlesme.py
yokatlas_py/fetchers/lise_alani_dagilimi.py
yokatlas_py/fetchers/lise_bazinda_yerlesen_dagilimi.py
yokatlas_py/fetchers/lise_grubu_ve_tipi_dagilimi.py
yokatlas_py/fetchers/mezuniyet_yili_cinsiyet_dagilimi.py
yokatlas_py/fetchers/mezuniyet_yili_dagilimi.py
yokatlas_py/fetchers/ogrenim_durumu.py
yokatlas_py/fetchers/okul_birincisi_yerlesen.py
yokatlas_py/fetchers/sehir_ve_cografi_bolge_dagilimi.py
yokatlas_py/fetchers/taban_puan_ve_basari_sirasi_istatistikleri.py
yokatlas_py/fetchers/tercih_edilen_iller.py
yokatlas_py/fetchers/tercih_edilen_program_turleri.py
yokatlas_py/fetchers/tercih_edilen_programlar.py
yokatlas_py/fetchers/tercih_edilen_universite_turleri.py
yokatlas_py/fetchers/tercih_edilen_universiteler.py
yokatlas_py/fetchers/tercih_istatistikleri.py
yokatlas_py/fetchers/tercih_kullanma_oranlari.py
yokatlas_py/fetchers/yatay_gecis_bilgileri.py
yokatlas_py/fetchers/yerlesen_basari_siralari.py
yokatlas_py/fetchers/yerlesen_il_dagilimi.py
yokatlas_py/fetchers/yerlesen_ortalama_netler.py
yokatlas_py/fetchers/yerlesen_puan_bilgileri.py
yokatlas_py/fetchers/yerlesen_son_kisi_bilgileri.py
yokatlas_py/fetchers/yerlesen_tercih_istatistikleri.py
yokatlas_py/lisans_fetchers/__init__.py
yokatlas_py/lisans_fetchers/akademisyen_sayilari.py
yokatlas_py-0.5.5.dist-info/licenses/LICENSE
yokatlas_py-0.5.5.dist-info/METADATA
yokatlas_py-0.5.5.dist-info/WHEEL
yokatlas_py-0.5.5.dist-info/top_level.txt
yokatlas_py-0.5.5.dist-info/RECORD
