Metadata-Version: 2.4
Name: yokatlas-py
Version: 0.5.5
Summary: A python wrapper for YOKATLAS API
Author-email: Said Sürücü <saidsrc@gmail.com>
License-Expression: MIT
Project-URL: Homepage, https://github.com/saidsurucu/yokatlas-py
Project-URL: Issues, https://github.com/saidsurucu/yokatlas-py/issues
Keywords: yokatlas,turkish-education,university,yok,higher-education,turkey,api
Classifier: Development Status :: 4 - Beta
Classifier: Intended Audience :: Developers
Classifier: Intended Audience :: Education
Classifier: Programming Language :: Python :: 3
Classifier: Programming Language :: Python :: 3.9
Classifier: Programming Language :: Python :: 3.10
Classifier: Programming Language :: Python :: 3.11
Classifier: Programming Language :: Python :: 3.12
Classifier: Topic :: Software Development :: Libraries :: Python Modules
Classifier: Topic :: Education
Classifier: Operating System :: OS Independent
Requires-Python: >=3.9
License-File: LICENSE
Requires-Dist: httpx>=0.28.1
Requires-Dist: urllib3>=1.26.0
Requires-Dist: beautifulsoup4>=4.9.0
Requires-Dist: pydantic==2.11.7
Requires-Dist: pydantic-settings>=2.0.0
Requires-Dist: typing-extensions>=4.0.0
Provides-Extra: dev
Requires-Dist: pytest>=6.0; extra == "dev"
Requires-Dist: pytest-asyncio>=0.18.0; extra == "dev"
Requires-Dist: pytest-cov>=2.10.0; extra == "dev"
Requires-Dist: black>=21.0.0; extra == "dev"
Requires-Dist: flake8>=3.8.0; extra == "dev"
Requires-Dist: mypy>=0.800; extra == "dev"
Provides-Extra: test
Requires-Dist: pytest>=6.0; extra == "test"
Requires-Dist: pytest-asyncio>=0.18.0; extra == "test"
Requires-Dist: responses>=0.18.0; extra == "test"
Dynamic: license-file
